LICENSE
MANIFEST.in
README.rst
setup.py
tse/__init__.py
tse/main.py
tse.egg-info/PKG-INFO
tse.egg-info/SOURCES.txt
tse.egg-info/dependency_links.txt
tse.egg-info/entry_points.txt
tse.egg-info/requires.txt
tse.egg-info/top_level.txt