Metadata-Version: 1.1
Name: tse
Version: 0.0.6
Summary: tse is an input stream editor in Python.
Home-page: https://github.com/atsuoishimoto/tse
Author: Atsuo Ishimoto
Author-email: ishimoto@gembook.org
License: MIT
Keywords: text filter
Platform: UNKNOWN
Classifier: Programming Language :: Python :: 2
Classifier: Programming Language :: Python :: 3
Classifier: Development Status :: 3 - Alpha
Classifier: Topic :: Text Processing :: Filters
Classifier: Topic :: Utilities
Classifier: License :: OSI Approved :: MIT License
